textual_colorpicker/__init__.py
textual_colorpicker/color_inputs.py
textual_colorpicker/color_picker.py
textual_colorpicker/color_preview.py
textual_colorpicker/hue_picker.py
textual_colorpicker/py.typed
textual_colorpicker/saturation_value_picker.py
textual_colorpicker-0.1.0.dist-info/licenses/LICENSE
textual_colorpicker-0.1.0.dist-info/METADATA
textual_colorpicker-0.1.0.dist-info/WHEEL
textual_colorpicker-0.1.0.dist-info/top_level.txt
textual_colorpicker-0.1.0.dist-info/RECORD
